contact_manager/__init__.py
contact_manager/admin.py
contact_manager/forms.py
contact_manager/models.py
contact_manager/tests.py
contact_manager/urls.py
contact_manager/views.py
contact_manager/fixtures/auth_users.json
contact_manager/fixtures/contact_form.json
contact_manager/fixtures/users.json
contact_manager/templates/contact/base.html
contact_manager/templates/contact/done.html
contact_manager/templates/contact/form.html
contact_manager/templates/contact/message_detail.html
contact_manager/templates/contact/message_list.html
contact_manager/templates/contact/simple_form.html
tango_contact_manager-0.10.0.dist-info/METADATA
tango_contact_manager-0.10.0.dist-info/RECORD
tango_contact_manager-0.10.0.dist-info/WHEEL
tango_contact_manager-0.10.0.dist-info/top_level.txt
