Metadata-Version: 1.1
Name: tango-contact-manager
Version: 0.10.0
Summary: Provides contact forms and any other user submission form you might want.
Home-page: https://github.com/tBaxter/tango-contact-manager
Author: Tim Baxter
Author-email: mail.baxter@gmail.com
License: LICENSE
Platform: UNKNOWN
Classifier: Development Status :: 4 - Beta
Classifier: Environment :: Web Environment
Classifier: Framework :: Django
Classifier: Intended Audience :: Developers
Classifier: License :: OSI Approved :: MIT License
Classifier: Programming Language :: Python
Classifier: Programming Language :: Python :: 2.7
Classifier: Programming Language :: Python :: 3.4
